odoo/addons/l10n_it_delivery_note_inter_company/README.rst
odoo/addons/l10n_it_delivery_note_inter_company/__init__.py
odoo/addons/l10n_it_delivery_note_inter_company/__manifest__.py
odoo/addons/l10n_it_delivery_note_inter_company/i18n/it.po
odoo/addons/l10n_it_delivery_note_inter_company/i18n/l10n_it_delivery_note_inter_company.pot
odoo/addons/l10n_it_delivery_note_inter_company/models/__init__.py
odoo/addons/l10n_it_delivery_note_inter_company/models/stock_delivery_note.py
odoo/addons/l10n_it_delivery_note_inter_company/readme/CONFIGURE.rst
odoo/addons/l10n_it_delivery_note_inter_company/readme/CONTRIBUTORS.rst
odoo/addons/l10n_it_delivery_note_inter_company/readme/DESCRIPTION.rst
odoo/addons/l10n_it_delivery_note_inter_company/readme/USAGE.rst
odoo/addons/l10n_it_delivery_note_inter_company/static/description/icon.png
odoo/addons/l10n_it_delivery_note_inter_company/static/description/index.html
odoo/addons/l10n_it_delivery_note_inter_company/tests/__init__.py
odoo/addons/l10n_it_delivery_note_inter_company/tests/test_delivery_note_inter_company.py
odoo/addons/l10n_it_delivery_note_inter_company/wizards/__init__.py
odoo/addons/l10n_it_delivery_note_inter_company/wizards/delivery_note_select.py
odoo/addons/l10n_it_delivery_note_inter_company/wizards/delivery_note_select.xml
odoo14_addon_l10n_it_delivery_note_inter_company-14.0.1.0.3.dist-info/METADATA
odoo14_addon_l10n_it_delivery_note_inter_company-14.0.1.0.3.dist-info/WHEEL
odoo14_addon_l10n_it_delivery_note_inter_company-14.0.1.0.3.dist-info/top_level.txt
odoo14_addon_l10n_it_delivery_note_inter_company-14.0.1.0.3.dist-info/RECORD
